petique.py
petique-0.1.0.dist-info/METADATA
petique-0.1.0.dist-info/WHEEL
petique-0.1.0.dist-info/entry_points.txt
petique-0.1.0.dist-info/licenses/COPYING.WTFPL
petique-0.1.0.dist-info/RECORD
