Metadata-Version: 2.4
Name: petique
Version: 0.1.0
Summary: re-nice processes basing on custom rules
Project-URL: Homepage, https://gitlab.com/hydrargyrum/petique
Author-email: Hg <dev@indigo.re>
License-Expression: WTFPL
License-File: COPYING.WTFPL
Keywords: cpu,io,nice,oom,ram
Requires-Python: >=3
Requires-Dist: psutil
